setup.py
c_excel_template/__init__.py
c_excel_template/excel_template.py
c_excel_template/setup.py
c_excel_template/test.py
c_excel_template.egg-info/PKG-INFO
c_excel_template.egg-info/SOURCES.txt
c_excel_template.egg-info/dependency_links.txt
c_excel_template.egg-info/requires.txt
c_excel_template.egg-info/top_level.txt